{
    "profiles": [
        {
            "complex_modifications": {
                "rules": [
                    {
                        "description": "Change Command+Tab to Control+Tab",
                        "manipulators": [
                            {
                                "from": {
                                    "key_code": "tab",
                                    "modifiers": {
                                        "mandatory": ["command"],
                                        "optional": ["any"]
                                    }
                                },
                                "to": [
                                    {
                                        "key_code": "tab",
                                        "modifiers": ["control"]
                                    }
                                ],
                                "type": "basic"
                            }
                        ]
                    },
                    {
                        "description": "Change Control+Tab to Command+Tab",
                        "manipulators": [
                            {
                                "from": {
                                    "key_code": "tab",
                                    "modifiers": {
                                        "mandatory": ["control"],
                                        "optional": ["any"]
                                    }
                                },
                                "to": [
                                    {
                                        "key_code": "tab",
                                        "modifiers": ["command"]
                                    }
                                ],
                                "type": "basic"
                            }
                        ]
                    },
                    {
                        "description": "Exchange command + arrow keys with option + arrow keys",
                        "manipulators": [
                            {
                                "from": {
                                    "key_code": "right_arrow",
                                    "modifiers": {
                                        "mandatory": ["command"],
                                        "optional": ["any"]
                                    }
                                },
                                "to": [
                                    {
                                        "key_code": "right_arrow",
                                        "modifiers": ["option"]
                                    }
                                ],
                                "type": "basic"
                            },
                            {
                                "from": {
                                    "key_code": "left_arrow",
                                    "modifiers": {
                                        "mandatory": ["command"],
                                        "optional": ["any"]
                                    }
                                },
                                "to": [
                                    {
                                        "key_code": "left_arrow",
                                        "modifiers": ["option"]
                                    }
                                ],
                                "type": "basic"
                            },
                            {
                                "from": {
                                    "key_code": "up_arrow",
                                    "modifiers": {
                                        "mandatory": ["command"],
                                        "optional": ["any"]
                                    }
                                },
                                "to": [
                                    {
                                        "key_code": "up_arrow",
                                        "modifiers": ["option"]
                                    }
                                ],
                                "type": "basic"
                            },
                            {
                                "from": {
                                    "key_code": "down_arrow",
                                    "modifiers": {
                                        "mandatory": ["command"],
                                        "optional": ["any"]
                                    }
                                },
                                "to": [
                                    {
                                        "key_code": "down_arrow",
                                        "modifiers": ["option"]
                                    }
                                ],
                                "type": "basic"
                            },
                            {
                                "from": {
                                    "key_code": "right_arrow",
                                    "modifiers": {
                                        "mandatory": ["option"],
                                        "optional": ["any"]
                                    }
                                },
                                "to": [
                                    {
                                        "key_code": "right_arrow",
                                        "modifiers": ["command"]
                                    }
                                ],
                                "type": "basic"
                            },
                            {
                                "from": {
                                    "key_code": "left_arrow",
                                    "modifiers": {
                                        "mandatory": ["option"],
                                        "optional": ["any"]
                                    }
                                },
                                "to": [
                                    {
                                        "key_code": "left_arrow",
                                        "modifiers": ["command"]
                                    }
                                ],
                                "type": "basic"
                            },
                            {
                                "from": {
                                    "key_code": "up_arrow",
                                    "modifiers": {
                                        "mandatory": ["option"],
                                        "optional": ["any"]
                                    }
                                },
                                "to": [
                                    {
                                        "key_code": "up_arrow",
                                        "modifiers": ["command"]
                                    }
                                ],
                                "type": "basic"
                            },
                            {
                                "from": {
                                    "key_code": "down_arrow",
                                    "modifiers": {
                                        "mandatory": ["option"],
                                        "optional": ["any"]
                                    }
                                },
                                "to": [
                                    {
                                        "key_code": "down_arrow",
                                        "modifiers": ["command"]
                                    }
                                ],
                                "type": "basic"
                            }
                        ]
                    },
                    {
                        "description": "Change Command+Backward-Delete and Option+Backward-Delete",
                        "manipulators": [
                            {
                                "from": {
                                    "key_code": "delete_or_backspace",
                                    "modifiers": {
                                        "mandatory": ["command"],
                                        "optional": ["any"]
                                    }
                                },
                                "to": [
                                    {
                                        "key_code": "delete_or_backspace",
                                        "modifiers": ["option"]
                                    }
                                ],
                                "type": "basic"
                            }
                        ]
                    },
                    {
                        "description": "Change Option+Backward-Delete to Command+Backward-Delete",
                        "manipulators": [
                            {
                                "from": {
                                    "key_code": "delete_or_backspace",
                                    "modifiers": {
                                        "mandatory": ["option"],
                                        "optional": ["any"]
                                    }
                                },
                                "to": [
                                    {
                                        "key_code": "delete_or_backspace",
                                        "modifiers": ["command"]
                                    }
                                ],
                                "type": "basic"
                            }
                        ]
                    },
                    {
                        "description": "Change Command+Forward-Delete to Option+Forward-Delete",
                        "manipulators": [
                            {
                                "from": {
                                    "key_code": "delete_forward",
                                    "modifiers": {
                                        "mandatory": ["command"],
                                        "optional": ["any"]
                                    }
                                },
                                "to": [
                                    {
                                        "key_code": "delete_forward",
                                        "modifiers": ["option"]
                                    }
                                ],
                                "type": "basic"
                            }
                        ]
                    },
                    {
                        "description": "Change Option+Forward-Delete to Command+Forward-Delete",
                        "manipulators": [
                            {
                                "from": {
                                    "key_code": "delete_forward",
                                    "modifiers": {
                                        "mandatory": ["option"],
                                        "optional": ["any"]
                                    }
                                },
                                "to": [
                                    {
                                        "key_code": "delete_forward",
                                        "modifiers": ["command"]
                                    }
                                ],
                                "type": "basic"
                            }
                        ]
                    },
                    {
                        "description": "Home to Command Left",
                        "manipulators": [
                            {
                                "conditions": [
                                    {
                                        "bundle_identifiers": [
                                            "^com\\.microsoft\\.rdc$",
                                            "^com\\.microsoft\\.rdc\\.mac$",
                                            "^com\\.microsoft\\.rdc\\.macos$",
                                            "^com\\.microsoft\\.rdc\\.osx\\.beta$",
                                            "^net\\.sf\\.cord$",
                                            "^com\\.thinomenon\\.RemoteDesktopConnection$",
                                            "^com\\.itap-mobile\\.qmote$",
                                            "^com\\.nulana\\.remotixmac$",
                                            "^com\\.p5sys\\.jump\\.mac\\.viewer$",
                                            "^com\\.p5sys\\.jump\\.mac\\.viewer\\.web$",
                                            "^com\\.teamviewer\\.TeamViewer$",
                                            "^com\\.vmware\\.horizon$",
                                            "^com\\.2X\\.Client\\.Mac$",
                                            "^com\\.vmware\\.fusion$",
                                            "^com\\.vmware\\.horizon$",
                                            "^com\\.vmware\\.view$",
                                            "^com\\.parallels\\.desktop$",
                                            "^com\\.parallels\\.vm$",
                                            "^com\\.parallels\\.desktop\\.console$",
                                            "^org\\.virtualbox\\.app\\.VirtualBoxVM$",
                                            "^com\\.citrix\\.XenAppViewer$",
                                            "^com\\.vmware\\.proxyApp\\.",
                                            "^com\\.parallels\\.winapp\\.",
                                            "^org\\.macports\\.X11$",
                                            "^com\\.apple\\.Terminal$",
                                            "^com\\.googlecode\\.iterm2$",
                                            "^co\\.zeit\\.hyperterm$",
                                            "^co\\.zeit\\.hyper$",
                                            "^io\\.alacritty$",
                                            "^net\\.kovidgoyal\\.kitty$",
                                            "^com\\.jetbrains\\.*"
                                        ],
                                        "type": "frontmost_application_unless"
                                    }
                                ],
                                "from": {
                                    "key_code": "home",
                                    "modifiers": { "optional": ["any"] }
                                },
                                "to": [
                                    {
                                        "key_code": "left_arrow",
                                        "modifiers": "command"
                                    }
                                ],
                                "type": "basic"
                            }
                        ]
                    },
                    {
                        "description": "End to Command Right",
                        "manipulators": [
                            {
                                "conditions": [
                                    {
                                        "bundle_identifiers": [
                                            "^com\\.microsoft\\.rdc$",
                                            "^com\\.microsoft\\.rdc\\.mac$",
                                            "^com\\.microsoft\\.rdc\\.macos$",
                                            "^com\\.microsoft\\.rdc\\.osx\\.beta$",
                                            "^net\\.sf\\.cord$",
                                            "^com\\.thinomenon\\.RemoteDesktopConnection$",
                                            "^com\\.itap-mobile\\.qmote$",
                                            "^com\\.nulana\\.remotixmac$",
                                            "^com\\.p5sys\\.jump\\.mac\\.viewer$",
                                            "^com\\.p5sys\\.jump\\.mac\\.viewer\\.web$",
                                            "^com\\.teamviewer\\.TeamViewer$",
                                            "^com\\.vmware\\.horizon$",
                                            "^com\\.2X\\.Client\\.Mac$",
                                            "^com\\.vmware\\.fusion$",
                                            "^com\\.vmware\\.horizon$",
                                            "^com\\.vmware\\.view$",
                                            "^com\\.parallels\\.desktop$",
                                            "^com\\.parallels\\.vm$",
                                            "^com\\.parallels\\.desktop\\.console$",
                                            "^org\\.virtualbox\\.app\\.VirtualBoxVM$",
                                            "^com\\.citrix\\.XenAppViewer$",
                                            "^com\\.vmware\\.proxyApp\\.",
                                            "^com\\.parallels\\.winapp\\.",
                                            "^org\\.macports\\.X11$",
                                            "^com\\.apple\\.Terminal$",
                                            "^com\\.googlecode\\.iterm2$",
                                            "^co\\.zeit\\.hyperterm$",
                                            "^co\\.zeit\\.hyper$",
                                            "^io\\.alacritty$",
                                            "^net\\.kovidgoyal\\.kitty$",
                                            "^com\\.jetbrains\\.*"
                                        ],
                                        "type": "frontmost_application_unless"
                                    }
                                ],
                                "from": {
                                    "key_code": "end",
                                    "modifiers": { "optional": ["any"] }
                                },
                                "to": [
                                    {
                                        "key_code": "right_arrow",
                                        "modifiers": "command"
                                    }
                                ],
                                "type": "basic"
                            }
                        ]
                    },
                    {
                        "description": "PageUp to Option Up",
                        "manipulators": [
                            {
                                "conditions": [
                                    {
                                        "bundle_identifiers": [
                                            "^com\\.microsoft\\.rdc$",
                                            "^com\\.microsoft\\.rdc\\.mac$",
                                            "^com\\.microsoft\\.rdc\\.macos$",
                                            "^com\\.microsoft\\.rdc\\.osx\\.beta$",
                                            "^net\\.sf\\.cord$",
                                            "^com\\.thinomenon\\.RemoteDesktopConnection$",
                                            "^com\\.itap-mobile\\.qmote$",
                                            "^com\\.nulana\\.remotixmac$",
                                            "^com\\.p5sys\\.jump\\.mac\\.viewer$",
                                            "^com\\.p5sys\\.jump\\.mac\\.viewer\\.web$",
                                            "^com\\.teamviewer\\.TeamViewer$",
                                            "^com\\.vmware\\.horizon$",
                                            "^com\\.2X\\.Client\\.Mac$",
                                            "^com\\.vmware\\.fusion$",
                                            "^com\\.vmware\\.horizon$",
                                            "^com\\.vmware\\.view$",
                                            "^com\\.parallels\\.desktop$",
                                            "^com\\.parallels\\.vm$",
                                            "^com\\.parallels\\.desktop\\.console$",
                                            "^org\\.virtualbox\\.app\\.VirtualBoxVM$",
                                            "^com\\.citrix\\.XenAppViewer$",
                                            "^com\\.vmware\\.proxyApp\\.",
                                            "^com\\.parallels\\.winapp\\.",
                                            "^org\\.macports\\.X11$",
                                            "^com\\.apple\\.Terminal$",
                                            "^com\\.googlecode\\.iterm2$",
                                            "^co\\.zeit\\.hyperterm$",
                                            "^co\\.zeit\\.hyper$",
                                            "^io\\.alacritty$",
                                            "^net\\.kovidgoyal\\.kitty$",
                                            "^com\\.jetbrains\\.*",
                                            "^com\\.mitchellh\\.ghostty"
                                        ],
                                        "type": "frontmost_application_unless"
                                    }
                                ],
                                "from": {
                                    "key_code": "page_up",
                                    "modifiers": { "optional": ["any"] }
                                },
                                "to": [
                                    {
                                        "key_code": "up_arrow",
                                        "modifiers": "option"
                                    }
                                ],
                                "type": "basic"
                            }
                        ]
                    },
                    {
                        "description": "PageDown to Option Down",
                        "manipulators": [
                            {
                                "conditions": [
                                    {
                                        "bundle_identifiers": [
                                            "^com\\.microsoft\\.rdc$",
                                            "^com\\.microsoft\\.rdc\\.mac$",
                                            "^com\\.microsoft\\.rdc\\.macos$",
                                            "^com\\.microsoft\\.rdc\\.osx\\.beta$",
                                            "^net\\.sf\\.cord$",
                                            "^com\\.thinomenon\\.RemoteDesktopConnection$",
                                            "^com\\.itap-mobile\\.qmote$",
                                            "^com\\.nulana\\.remotixmac$",
                                            "^com\\.p5sys\\.jump\\.mac\\.viewer$",
                                            "^com\\.p5sys\\.jump\\.mac\\.viewer\\.web$",
                                            "^com\\.teamviewer\\.TeamViewer$",
                                            "^com\\.vmware\\.horizon$",
                                            "^com\\.2X\\.Client\\.Mac$",
                                            "^com\\.vmware\\.fusion$",
                                            "^com\\.vmware\\.horizon$",
                                            "^com\\.vmware\\.view$",
                                            "^com\\.parallels\\.desktop$",
                                            "^com\\.parallels\\.vm$",
                                            "^com\\.parallels\\.desktop\\.console$",
                                            "^org\\.virtualbox\\.app\\.VirtualBoxVM$",
                                            "^com\\.citrix\\.XenAppViewer$",
                                            "^com\\.vmware\\.proxyApp\\.",
                                            "^com\\.parallels\\.winapp\\.",
                                            "^org\\.macports\\.X11$",
                                            "^com\\.apple\\.Terminal$",
                                            "^com\\.googlecode\\.iterm2$",
                                            "^co\\.zeit\\.hyperterm$",
                                            "^co\\.zeit\\.hyper$",
                                            "^io\\.alacritty$",
                                            "^net\\.kovidgoyal\\.kitty$",
                                            "^com\\.jetbrains\\.*",
                                            "^com\\.mitchellh\\.ghostty"
                                        ],
                                        "type": "frontmost_application_unless"
                                    }
                                ],
                                "from": {
                                    "key_code": "page_down",
                                    "modifiers": { "optional": ["any"] }
                                },
                                "to": [
                                    {
                                        "key_code": "down_arrow",
                                        "modifiers": "option"
                                    }
                                ],
                                "type": "basic"
                            }
                        ]
                    }
                ]
            },
            "devices": [
                {
                    "identifiers": {
                        "is_keyboard": true,
                        "product_id": 832,
                        "vendor_id": 1452
                    },
                    "simple_modifications": [
                        {
                            "from": { "key_code": "left_command" },
                            "to": [{ "key_code": "left_control" }]
                        },
                        {
                            "from": { "key_code": "left_control" },
                            "to": [{ "key_code": "left_command" }]
                        }
                    ]
                },
                {
                    "identifiers": {
                        "is_keyboard": true,
                        "product_id": 24672,
                        "vendor_id": 65261
                    },
                    "simple_modifications": [
                        {
                            "from": { "key_code": "backslash" },
                            "to": [{ "key_code": "quote" }]
                        },
                        {
                            "from": { "key_code": "left_command" },
                            "to": [{ "key_code": "left_control" }]
                        },
                        {
                            "from": { "key_code": "left_control" },
                            "to": [{ "key_code": "left_command" }]
                        }
                    ]
                },
                {
                    "identifiers": {
                        "is_keyboard": true,
                        "product_id": 49291,
                        "vendor_id": 1133
                    },
                    "ignore": true,
                    "manipulate_caps_lock_led": false
                }
            ],
            "name": "Default profile",
            "selected": true,
            "virtual_hid_keyboard": {
                "country_code": 0,
                "keyboard_type_v2": "ansi"
            }
        }
    ]
}